odoo10_addon_donation_bank_statement-10.0.1.0.0-py2.7-nspkg.pth
odoo/addons/donation_bank_statement/README.rst
odoo/addons/donation_bank_statement/__init__.py
odoo/addons/donation_bank_statement/__manifest__.py
odoo/addons/donation_bank_statement/demo/demo.xml
odoo/addons/donation_bank_statement/i18n/donation_bank_statement.pot
odoo/addons/donation_bank_statement/i18n/fr.po
odoo/addons/donation_bank_statement/models/__init__.py
odoo/addons/donation_bank_statement/models/account_config_settings.py
odoo/addons/donation_bank_statement/models/bank_statement.py
odoo/addons/donation_bank_statement/models/company.py
odoo/addons/donation_bank_statement/models/donation.py
odoo/addons/donation_bank_statement/security/ir.model.access.csv
odoo/addons/donation_bank_statement/static/description/icon.png
odoo/addons/donation_bank_statement/views/account_config_settings.xml
odoo/addons/donation_bank_statement/views/bank_statement.xml
odoo/addons/donation_bank_statement/views/donation.xml
odoo10_addon_donation_bank_statement-10.0.1.0.0.dist-info/DESCRIPTION.rst
odoo10_addon_donation_bank_statement-10.0.1.0.0.dist-info/METADATA
odoo10_addon_donation_bank_statement-10.0.1.0.0.dist-info/RECORD
odoo10_addon_donation_bank_statement-10.0.1.0.0.dist-info/WHEEL
odoo10_addon_donation_bank_statement-10.0.1.0.0.dist-info/metadata.json
odoo10_addon_donation_bank_statement-10.0.1.0.0.dist-info/namespace_packages.txt
odoo10_addon_donation_bank_statement-10.0.1.0.0.dist-info/top_level.txt
